quality_estimation/__init__.py
quality_estimation/engine.py
quality_estimation/server.py
quality_estimation-0.1.0.dist-info/WHEEL
quality_estimation-0.1.0.dist-info/METADATA
quality_estimation-0.1.0.dist-info/RECORD
